{
    "version": "1.0",
    "properties": {
        "@context": {
            "anyOf": [
                {
                    "type": "string"
                },
                {
                    "type": "object"
                },
                {
                    "type": "array"
                }
            ],
            "description": "The JSON-LD context"
        },
        "date": {
            "format": "date-time",
            "type": "string",
            "description": "A date following the ISO8601 standard."
        },
        "@id": {
            "format": "uri",
            "type": "string",
            "description": "The JSON-LD identifier"
        },
        "type": {
            "$ref": "annotation_schema.json#",
            "description": "The type of date, used to specify the process which is being timestamped by the date attribute value, ideally comes from a controlled terminology."
        },
        "@type": {
            "type": "string",
            "enum": [
                "Date"
            ],
            "description": "The JSON-LD type"
        }
    },
    "title": "MIACME date schema",
    "additionalProperties": false,
    "type": "object",
    "description": "Information about a calendar date or timestamp indicating day, month, year and time of an event.",
    "id": "https://w3id.org/mircat/miacme_miaca_merge/schema/date_schema.json",
    "required": [
        "date",
        "type"
    ],
    "$schema": "http://json-schema.org/draft-04/schema"
}